xiuxian_sect/__init__.py
xiuxian_sect/sectconfig.py
xiuxian_sect-0.30.dist-info/METADATA
xiuxian_sect-0.30.dist-info/WHEEL
xiuxian_sect-0.30.dist-info/top_level.txt
xiuxian_sect-0.30.dist-info/RECORD
